varitykit/__init__.py
varitykit/cli/__init__.py
varitykit/cli/ai_init.py
varitykit/cli/bootstrap.py
varitykit/cli/completions.py
varitykit/cli/contract.py
varitykit/cli/deploy.py
varitykit/cli/dev.py
varitykit/cli/doctor.py
varitykit/cli/fund.py
varitykit/cli/init.py
varitykit/cli/localdepin.py
varitykit/cli/localnet.py
varitykit/cli/main.py
varitykit/cli/marketing.py
varitykit/cli/marketplace.py
varitykit/cli/migrate.py
varitykit/cli/task.py
varitykit/cli/template.py
varitykit/cli/thirdweb.py
varitykit/core/__init__.py
varitykit/core/ai_engine.py
varitykit/core/build_manager.py
varitykit/core/config.py
varitykit/core/contract_verifier.py
varitykit/core/deployment_history.py
varitykit/core/deployment_orchestrator.py
varitykit/core/deployment_tracker.py
varitykit/core/errors.py
varitykit/core/gas_estimator.py
varitykit/core/ipfs_uploader.py
varitykit/core/project_detector.py
varitykit/core/sdk_config.py
varitykit/core/sdk_wrapper.py
varitykit/core/template_generator.py
varitykit/core/templates.py
varitykit/core/types.py
varitykit/core/url_service.py
varitykit/utils/__init__.py
varitykit/utils/logger.py
varitykit/utils/progress.py
varitykit/utils/token.py
varitykit/utils/validators.py
varitykit-1.0.0.dist-info/LICENSE
varitykit-1.0.0.dist-info/METADATA
varitykit-1.0.0.dist-info/WHEEL
varitykit-1.0.0.dist-info/entry_points.txt
varitykit-1.0.0.dist-info/top_level.txt
varitykit-1.0.0.dist-info/RECORD
