Metadata-Version: 2.1
Name: varitykit
Version: 1.0.0
Summary: AI-powered CLI for building dashboards on Varity L3
Author-email: Varity Team <hello@varity.com>
License: MIT
Project-URL: Homepage, https://varity.ai
Project-URL: Documentation, https://docs.varity.ai/varitykit
Project-URL: Repository, https://github.com/varity-ai/varitykit-cli
Project-URL: Bug Tracker, https://github.com/varity-ai/varitykit-cli/issues
Keywords: varity,blockchain,depin,ai,dashboard,cli,web3
Classifier: Development Status :: 4 - Beta
Classifier: Intended Audience :: Developers
Classifier: License :: OSI Approved :: MIT License
Classifier: Programming Language :: Python :: 3
Classifier: Programming Language :: Python :: 3.8
Classifier: Programming Language :: Python :: 3.9
Classifier: Programming Language :: Python :: 3.10
Classifier: Programming Language :: Python :: 3.11
Classifier: Programming Language :: Python :: 3.12
Classifier: Topic :: Software Development :: Build Tools
Classifier: Topic :: Software Development :: Libraries :: Python Modules
Requires-Python: >=3.8
License-File: LICENSE
Requires-Dist: click>=8.1.0
Requires-Dist: docker>=6.0.0
Requires-Dist: pyyaml>=6.0
Requires-Dist: requests>=2.31.0
Requires-Dist: rich>=13.0.0
Requires-Dist: toml>=0.10.2
Requires-Dist: jinja2>=3.1.0
Requires-Dist: python-dotenv>=1.0.0
Requires-Dist: aiohttp>=3.10.0
Requires-Dist: authlib>=1.3.0
Requires-Dist: ecdsa>=0.18.0
Requires-Dist: python-jose>=3.3.0
Requires-Dist: black>=24.3.0
Requires-Dist: copier>=9.0.0
Requires-Dist: pillow>=10.3.0
Requires-Dist: pynacl>=1.5.0
Requires-Dist: configobj>=5.0.8
Requires-Dist: fastapi>=0.109.1
Requires-Dist: filelock>=3.13.0
Requires-Dist: h2>=4.1.0
Requires-Dist: idna>=3.7
Requires-Dist: marshmallow>=3.21.0
Requires-Dist: python-multipart>=0.0.7
Requires-Dist: fonttools>=4.50.0
Provides-Extra: all
Requires-Dist: web3>=6.0.0; extra == "all"
Requires-Dist: eth-account>=0.10.0; extra == "all"
Requires-Dist: eth-utils>=2.3.0; extra == "all"
Requires-Dist: psutil>=5.9.0; extra == "all"
Provides-Extra: blockchain
Requires-Dist: web3>=6.0.0; extra == "blockchain"
Requires-Dist: eth-account>=0.10.0; extra == "blockchain"
Requires-Dist: eth-utils>=2.3.0; extra == "blockchain"
Provides-Extra: dev
Requires-Dist: pytest>=7.4.0; extra == "dev"
Requires-Dist: pytest-cov>=4.1.0; extra == "dev"
Requires-Dist: pytest-mock>=3.12.0; extra == "dev"
Requires-Dist: ruff>=0.1.0; extra == "dev"
Requires-Dist: mypy>=1.7.0; extra == "dev"
Requires-Dist: types-requests>=2.31.0; extra == "dev"
Requires-Dist: types-toml>=0.10.0; extra == "dev"
Requires-Dist: types-PyYAML>=6.0.0; extra == "dev"
Requires-Dist: types-click>=7.1.0; extra == "dev"
Requires-Dist: isort>=5.12.0; extra == "dev"
Requires-Dist: autoflake>=2.2.0; extra == "dev"
